cipheydists/__init__.py
cipheydists/brandon/english.json
cipheydists/charset/asciiTable.json
cipheydists/charset/encodings.json
cipheydists/charset/english.json
cipheydists/dist/english.json
cipheydists/dist/lcase.json
cipheydists/dist/twist.json
cipheydists/list/base69.json
cipheydists/list/english.json
cipheydists/list/english1000.json
cipheydists/list/English5000Freq.json
cipheydists/list/englishAlphabet.json
cipheydists/list/englishStopWords.json
cipheydists/list/flags.json
cipheydists/list/urls.json
cipheydists/model/.gitattributes
cipheydists/model/cipher_detector.tflite
cipheydists/model/english_sentence.tflite
cipheydists/translate/baconian.json
cipheydists/translate/baudot.json
cipheydists/translate/dna.json
cipheydists/translate/dtmf.json
cipheydists/translate/galactic.json
cipheydists/translate/leet.json
cipheydists/translate/morse.json
cipheydists/translate/ook.json
cipheydists/translate/soundex.json
cipheydists/translate/tap_code.json
cipheydists-0.3.33.dist-info/LICENSE
cipheydists-0.3.33.dist-info/WHEEL
cipheydists-0.3.33.dist-info/METADATA
cipheydists-0.3.33.dist-info/RECORD
